{"symbol": "AGRO", "annualReports": [{"fiscalDateEnding": "2019-12-31", "reportedCurrency": "USD", "totalAssets": "2521307000", "intangibleAssets": "13659000", "earningAssets": "None", "otherCurrentAssets": "117227000", "totalLiabilities": "1492424000", "totalShareholderEquity": "988269000", "deferredLongTermLiabilities": "None", "otherCurrentLiabilities": "1423000", "commonStock": "183573000", "retainedEarnings": "206669000", "otherLiabilities": "173252000", "goodwill": "20020000", "otherAssets": "95892000", "cash": "290276000", "totalCurrentLiabilities": "364400000", "shortTermDebt": "27000", "currentLongTermDebt": "188078000", "otherShareholderEquity": "-295766000", "propertyPlantEquipment": "1742670000", "totalCurrentAssets": "649066000", "longTermInvestments": "None", "netTangibleAssets": "954590000", "shortTermInvestments": "None", "netReceivables": "51498000", "longTermDebt": "780202000", "inventory": "112790000", "accountsPayable": "90594000", "totalPermanentEquity": "None", "additionalPaidInCapital": "None", "commonStockTotalEquity": "None", "preferredStockTotalEquity": "None", "retainedEarningsTotalEquity": "None", "treasuryStock": "-7946000", "accumulatedAmortization": "None", "otherNonCurrrentAssets": "16933000", "deferredLongTermAssetCharges": "None", "totalNonCurrentAssets": "1872241000", "capitalLeaseObligations": "216384000", "totalLongTermDebt": "954772000", "otherNonCurrentLiabilities": "None", "totalNonCurrentLiabilities": "1128024000", "negativeGoodwill": "None", "warrants": "None", "preferredStockRedeemable": "None", "capitalSurplus": "901739000", "liabilitiesAndShareholderEquity": "None", "cashAndShortTermInvestments": "290276000", "accumulatedDepreciation": "None", "commonStockSharesOutstanding": "118000000"}, {"fiscalDateEnding": "2018-12-31", "reportedCurrency": "USD", "totalAssets": "2277372000", "intangibleAssets": "6559000", "earningAssets": "None", "otherCurrentAssets": "94125000", "totalLiabilities": "1169227000", "totalShareholderEquity": "1063636000", "deferredLongTermLiabilities": "None", "otherCurrentLiabilities": "283000", "commonStock": "183573000", "retainedEarnings": "237188000", "otherLiabilities": "172897000", "goodwill": "21350000", "otherAssets": "98331000", "cash": "273635000", "totalCurrentLiabilities": "277846000", "shortTermDebt": "2320000", "currentLongTermDebt": "143432000", "otherShareholderEquity": "-248887000", "propertyPlantEquipment": "1490298000", "totalCurrentAssets": "660834000", "longTermInvestments": "None", "netTangibleAssets": "1035727000", "shortTermInvestments": "None", "netReceivables": "66001000", "longTermDebt": "718089000", "inventory": "128102000", "accountsPayable": "94483000", "totalPermanentEquity": "None", "additionalPaidInCapital": "None", "commonStockTotalEquity": "None", "preferredStockTotalEquity": "None", "retainedEarningsTotalEquity": "None", "treasuryStock": "-8741000", "accumulatedAmortization": "None", "otherNonCurrrentAssets": "15362000", "deferredLongTermAssetCharges": "None", "totalNonCurrentAssets": "1616538000", "capitalLeaseObligations": "595000", "totalLongTermDebt": "718484000", "otherNonCurrentLiabilities": "None", "totalNonCurrentLiabilities": "891381000", "negativeGoodwill": "None", "warrants": "None", "preferredStockRedeemable": "None", "capitalSurplus": "900503000", "liabilitiesAndShareholderEquity": "None", "cashAndShortTermInvestments": "273635000", "accumulatedDepreciation": "None", "commonStockSharesOutstanding": "118000000"}, {"fiscalDateEnding": "2017-12-31", "reportedCurrency": "USD", "totalAssets": "1607201000", "intangibleAssets": "4780000", "earningAssets": "None", "otherCurrentAssets": "156748000", "totalLiabilities": "962070000", "totalShareholderEquity": "639714000", "deferredLongTermLiabilities": "10457000", "otherCurrentLiabilities": "552000", "commonStock": "183573000", "retainedEarnings": "60984000", "otherLiabilities": "16602000", "goodwill": "12412000", "otherAssets": "98079000", "cash": "269195000", "totalCurrentLiabilities": "282408000", "shortTermDebt": "6214000", "currentLongTermDebt": "154831000", "otherShareholderEquity": "-517869000", "propertyPlantEquipment": "840366000", "totalCurrentAssets": "689452000", "longTermInvestments": "24378000", "netTangibleAssets": "656688000", "shortTermInvestments": "380000", "netReceivables": "52294000", "longTermDebt": "663022000", "inventory": "108919000", "accountsPayable": "82824000", "totalPermanentEquity": "None", "additionalPaidInCapital": "None", "commonStockTotalEquity": "None", "preferredStockTotalEquity": "None", "retainedEarningsTotalEquity": "None", "treasuryStock": "-6967000", "accumulatedAmortization": "None", "otherNonCurrrentAssets": "15002000", "deferredLongTermAssetCharges": "None", "totalNonCurrentAssets": "917749000", "capitalLeaseObligations": "105000", "totalLongTermDebt": "663060000", "otherNonCurrentLiabilities": "None", "totalNonCurrentLiabilities": "679662000", "negativeGoodwill": "None", "warrants": "None", "preferredStockRedeemable": "None", "capitalSurplus": "908934000", "liabilitiesAndShareholderEquity": "None", "cashAndShortTermInvestments": "269195000", "accumulatedDepreciation": "None", "commonStockSharesOutstanding": "121000000"}, {"fiscalDateEnding": "2016-12-31", "reportedCurrency": "USD", "totalAssets": "1455766000", "intangibleAssets": "3847000", "earningAssets": "None", "otherCurrentAssets": "136912000", "totalLiabilities": "784093000", "totalShareholderEquity": "664091000", "deferredLongTermLiabilities": "14689000", "otherCurrentLiabilities": "6406000", "commonStock": "183573000", "retainedEarnings": "50998000", "otherLiabilities": "21312000", "goodwill": "13405000", "otherAssets": "96118000", "cash": "158568000", "totalCurrentLiabilities": "332477000", "shortTermDebt": "205013000", "currentLongTermDebt": "205013000", "otherShareholderEquity": "-511627000", "propertyPlantEquipment": "814867000", "totalCurrentAssets": "568160000", "longTermInvestments": "0", "netTangibleAssets": "683082000", "shortTermInvestments": "3546000", "netReceivables": "69017000", "longTermDebt": "430202000", "inventory": "111754000", "accountsPayable": "77325000", "totalPermanentEquity": "None", "additionalPaidInCapital": "None", "commonStockTotalEquity": "None", "preferredStockTotalEquity": "None", "retainedEarningsTotalEquity": "None", "treasuryStock": "-1859000", "accumulatedAmortization": "None", "otherNonCurrrentAssets": "12362000", "deferredLongTermAssetCharges": "None", "totalNonCurrentAssets": "887606000", "capitalLeaseObligations": "181000", "totalLongTermDebt": "None", "otherNonCurrentLiabilities": "None", "totalNonCurrentLiabilities": "451616000", "negativeGoodwill": "None", "warrants": "None", "preferredStockRedeemable": "None", "capitalSurplus": "None", "liabilitiesAndShareholderEquity": "None", "cashAndShortTermInvestments": "None", "accumulatedDepreciation": "None", "commonStockSharesOutstanding": "123000000"}, {"fiscalDateEnding": "2015-12-31", "reportedCurrency": "USD", "totalAssets": "1355394000", "intangibleAssets": "3151000", "earningAssets": "None", "otherCurrentAssets": "17037000", "totalLiabilities": "827975000", "totalShareholderEquity": "520084000", "deferredLongTermLiabilities": "15636000", "otherCurrentLiabilities": "11712000", "commonStock": "183573000", "retainedEarnings": "48795000", "otherLiabilities": "20555000", "goodwill": "13510000", "otherAssets": "96002000", "cash": "198894000", "totalCurrentLiabilities": "323769000", "shortTermDebt": "239468000", "currentLongTermDebt": "239468000", "otherShareholderEquity": "-648022000", "propertyPlantEquipment": "703349000", "totalCurrentAssets": "539382000", "longTermInvestments": "26591000", "netTangibleAssets": "503423000", "shortTermInvestments": "6000", "netReceivables": "128909000", "longTermDebt": "483583000", "inventory": "190628000", "accountsPayable": "47500000", "totalPermanentEquity": "None", "additionalPaidInCapital": "None", "commonStockTotalEquity": "None", "preferredStockTotalEquity": "None", "retainedEarningsTotalEquity": "None", "treasuryStock": "-1936000", "accumulatedAmortization": "None", "otherNonCurrrentAssets": "None", "deferredLongTermAssetCharges": "None", "totalNonCurrentAssets": "None", "capitalLeaseObligations": "None", "totalLongTermDebt": "None", "otherNonCurrentLiabilities": "None", "totalNonCurrentLiabilities": "None", "negativeGoodwill": "None", "warrants": "None", "preferredStockRedeemable": "None", "capitalSurplus": "None", "liabilitiesAndShareholderEquity": "None", "cashAndShortTermInvestments": "None", "accumulatedDepreciation": "None", "commonStockSharesOutstanding": "122000000"}], "quarterlyReports": [{"fiscalDateEnding": "2020-06-30", "reportedCurrency": "USD", "totalAssets": "2312272000", "intangibleAssets": "None", "earningAssets": "None", "otherCurrentAssets": "73516000", "totalLiabilities": "1447778000", "totalShareholderEquity": "823323000", "deferredLongTermLiabilities": "None", "otherCurrentLiabilities": "2224000", "commonStock": "183573000", "retainedEarnings": "137983000", "otherLiabilities": "184677000", "goodwill": "None", "otherAssets": "115456000", "cash": "236259000", "totalCurrentLiabilities": "392684000", "shortTermDebt": "None", "currentLongTermDebt": "253421000", "otherShareholderEquity": "-396330000", "propertyPlantEquipment": "1569381000", "totalCurrentAssets": "596847000", "longTermInvestments": "None", "netTangibleAssets": "792735000", "shortTermInvestments": "None", "netReceivables": "121695000", "longTermDebt": "724464000", "inventory": "164968000", "accountsPayable": "83763000", "totalPermanentEquity": "None", "additionalPaidInCapital": "None", "commonStockTotalEquity": "None", "preferredStockTotalEquity": "None", "retainedEarningsTotalEquity": "None", "treasuryStock": "None", "accumulatedAmortization": "None", "otherNonCurrrentAssets": "13773000", "deferredLongTermAssetCharges": "None", "totalNonCurrentAssets": "1715425000", "capitalLeaseObligations": "179912000", "totalLongTermDebt": "None", "otherNonCurrentLiabilities": "None", "totalNonCurrentLiabilities": "1055094000", "negativeGoodwill": "None", "warrants": "None", "preferredStockRedeemable": "None", "capitalSurplus": "None", "liabilitiesAndShareholderEquity": "None", "cashAndShortTermInvestments": "None", "accumulatedDepreciation": "None", "commonStockSharesOutstanding": "None"}, {"fiscalDateEnding": "2020-03-31", "reportedCurrency": "USD", "totalAssets": "2336963000", "intangibleAssets": "13123000", "earningAssets": "None", "otherCurrentAssets": "91973000", "totalLiabilities": "1443212000", "totalShareholderEquity": "852396000", "deferredLongTermLiabilities": "None", "otherCurrentLiabilities": "4631000", "commonStock": "183573000", "retainedEarnings": "146352000", "otherLiabilities": "179725000", "goodwill": "18824000", "otherAssets": "115597000", "cash": "235425000", "totalCurrentLiabilities": "364150000", "shortTermDebt": "None", "currentLongTermDebt": "205316000", "otherShareholderEquity": "-369889000", "propertyPlantEquipment": "1619209000", "totalCurrentAssets": "570210000", "longTermInvestments": "None", "netTangibleAssets": "820449000", "shortTermInvestments": "None", "netReceivables": "41497000", "longTermDebt": "741526000", "inventory": "121584000", "accountsPayable": "84876000", "totalPermanentEquity": "None", "additionalPaidInCapital": "None", "commonStockTotalEquity": "None", "preferredStockTotalEquity": "None", "retainedEarningsTotalEquity": "None", "treasuryStock": "-8384000", "accumulatedAmortization": "None", "otherNonCurrrentAssets": "16915000", "deferredLongTermAssetCharges": "None", "totalNonCurrentAssets": "1766753000", "capitalLeaseObligations": "195715000", "totalLongTermDebt": "899337000", "otherNonCurrentLiabilities": "None", "totalNonCurrentLiabilities": "1079062000", "negativeGoodwill": "None", "warrants": "None", "preferredStockRedeemable": "None", "capitalSurplus": "900744000", "liabilitiesAndShareholderEquity": "None", "cashAndShortTermInvestments": "235425000", "accumulatedDepreciation": "None", "commonStockSharesOutstanding": "117000000"}, {"fiscalDateEnding": "2019-12-31", "reportedCurrency": "USD", "totalAssets": "2521307000", "intangibleAssets": "13659000", "earningAssets": "None", "otherCurrentAssets": "117227000", "totalLiabilities": "1492424000", "totalShareholderEquity": "988269000", "deferredLongTermLiabilities": "None", "otherCurrentLiabilities": "1423000", "commonStock": "183573000", "retainedEarnings": "206669000", "otherLiabilities": "173252000", "goodwill": "20020000", "otherAssets": "95892000", "cash": "290276000", "totalCurrentLiabilities": "364400000", "shortTermDebt": "27000", "currentLongTermDebt": "188078000", "otherShareholderEquity": "-295766000", "propertyPlantEquipment": "1742670000", "totalCurrentAssets": "649066000", "longTermInvestments": "None", "netTangibleAssets": "954590000", "shortTermInvestments": "None", "netReceivables": "51498000", "longTermDebt": "780202000", "inventory": "112790000", "accountsPayable": "90594000", "totalPermanentEquity": "None", "additionalPaidInCapital": "None", "commonStockTotalEquity": "None", "preferredStockTotalEquity": "None", "retainedEarningsTotalEquity": "None", "treasuryStock": "-7946000", "accumulatedAmortization": "None", "otherNonCurrrentAssets": "16933000", "deferredLongTermAssetCharges": "None", "totalNonCurrentAssets": "1872241000", "capitalLeaseObligations": "216384000", "totalLongTermDebt": "954772000", "otherNonCurrentLiabilities": "None", "totalNonCurrentLiabilities": "1128024000", "negativeGoodwill": "None", "warrants": "None", "preferredStockRedeemable": "None", "capitalSurplus": "901739000", "liabilitiesAndShareholderEquity": "None", "cashAndShortTermInvestments": "290276000", "accumulatedDepreciation": "None", "commonStockSharesOutstanding": "118000000"}, {"fiscalDateEnding": "2019-09-30", "reportedCurrency": "USD", "totalAssets": "2372554000", "intangibleAssets": "12092000", "earningAssets": "None", "otherCurrentAssets": "83351000", "totalLiabilities": "1376851000", "totalShareholderEquity": "954930000", "deferredLongTermLiabilities": "None", "otherCurrentLiabilities": "459000", "commonStock": "183573000", "retainedEarnings": "209248000", "otherLiabilities": "160784000", "goodwill": "18836000", "otherAssets": "94657000", "cash": "145833000", "totalCurrentLiabilities": "358922000", "shortTermDebt": "5207000", "currentLongTermDebt": "205564000", "otherShareholderEquity": "-334205000", "propertyPlantEquipment": "1690605000", "totalCurrentAssets": "556364000", "longTermInvestments": "None", "netTangibleAssets": "924002000", "shortTermInvestments": "None", "netReceivables": "57095000", "longTermDebt": "693703000", "inventory": "191558000", "accountsPayable": "71365000", "totalPermanentEquity": "None", "additionalPaidInCapital": "None", "commonStockTotalEquity": "None", "preferredStockTotalEquity": "None", "retainedEarningsTotalEquity": "None", "treasuryStock": "-7349000", "accumulatedAmortization": "None", "otherNonCurrrentAssets": "15954000", "deferredLongTermAssetCharges": "None", "totalNonCurrentAssets": "1816190000", "capitalLeaseObligations": "200973000", "totalLongTermDebt": "857145000", "otherNonCurrentLiabilities": "None", "totalNonCurrentLiabilities": "1017929000", "negativeGoodwill": "None", "warrants": "None", "preferredStockRedeemable": "None", "capitalSurplus": "903663000", "liabilitiesAndShareholderEquity": "None", "cashAndShortTermInvestments": "145833000", "accumulatedDepreciation": "None", "commonStockSharesOutstanding": "117000000"}, {"fiscalDateEnding": "2019-06-30", "reportedCurrency": "USD", "totalAssets": "2583527000", "intangibleAssets": "14305000", "earningAssets": "None", "otherCurrentAssets": "84982000", "totalLiabilities": "1436829000", "totalShareholderEquity": "1100965000", "deferredLongTermLiabilities": "None", "otherCurrentLiabilities": "3762000", "commonStock": "183573000", "retainedEarnings": "247718000", "otherLiabilities": "189212000", "goodwill": "22067000", "otherAssets": "97573000", "cash": "137990000", "totalCurrentLiabilities": "368661000", "shortTermDebt": "13972000", "currentLongTermDebt": "206747000", "otherShareholderEquity": "-228377000", "propertyPlantEquipment": "1874622000", "totalCurrentAssets": "574960000", "longTermInvestments": "None", "netTangibleAssets": "1064593000", "shortTermInvestments": "None", "netReceivables": "64169000", "longTermDebt": "706469000", "inventory": "200853000", "accountsPayable": "76200000", "totalPermanentEquity": "None", "additionalPaidInCapital": "None", "commonStockTotalEquity": "None", "preferredStockTotalEquity": "None", "retainedEarningsTotalEquity": "None", "treasuryStock": "-6907000", "accumulatedAmortization": "None", "otherNonCurrrentAssets": "17864000", "deferredLongTermAssetCharges": "None", "totalNonCurrentAssets": "2008567000", "capitalLeaseObligations": "215166000", "totalLongTermDebt": "878956000", "otherNonCurrentLiabilities": "None", "totalNonCurrentLiabilities": "1068168000", "negativeGoodwill": "None", "warrants": "None", "preferredStockRedeemable": "None", "capitalSurplus": "904958000", "liabilitiesAndShareholderEquity": "None", "cashAndShortTermInvestments": "137990000", "accumulatedDepreciation": "None", "commonStockSharesOutstanding": "118000000"}, {"fiscalDateEnding": "2019-03-31", "reportedCurrency": "USD", "totalAssets": "2471061000", "intangibleAssets": "12865000", "earningAssets": "None", "otherCurrentAssets": "37486000", "totalLiabilities": "1420387000", "totalShareholderEquity": "1050674000", "deferredLongTermLiabilities": "None", "otherCurrentLiabilities": "1006000", "commonStock": "183573000", "retainedEarnings": "232745000", "otherLiabilities": "183555000", "goodwill": "20210000", "otherAssets": "18198000", "cash": "156889000", "totalCurrentLiabilities": "337434000", "shortTermDebt": "10811000", "currentLongTermDebt": "175299000", "otherShareholderEquity": "-640606000", "propertyPlantEquipment": "1845987000", "totalCurrentAssets": "524845000", "longTermInvestments": "None", "netTangibleAssets": "1017599000", "shortTermInvestments": "None", "netReceivables": "58647000", "longTermDebt": "710658000", "inventory": "229323000", "accountsPayable": "86541000", "totalPermanentEquity": "None", "additionalPaidInCapital": "None", "commonStockTotalEquity": "None", "preferredStockTotalEquity": "None", "retainedEarningsTotalEquity": "None", "treasuryStock": "-8741000", "accumulatedAmortization": "None", "otherNonCurrrentAssets": "16644000", "deferredLongTermAssetCharges": "None", "totalNonCurrentAssets": "1946216000", "capitalLeaseObligations": "178259000", "totalLongTermDebt": "854033000", "otherNonCurrentLiabilities": "None", "totalNonCurrentLiabilities": "1037588000", "negativeGoodwill": "None", "warrants": "None", "preferredStockRedeemable": "None", "capitalSurplus": "900503000", "liabilitiesAndShareholderEquity": "None", "cashAndShortTermInvestments": "156889000", "accumulatedDepreciation": "None", "commonStockSharesOutstanding": "117000000"}, {"fiscalDateEnding": "2018-12-31", "reportedCurrency": "USD", "totalAssets": "2277372000", "intangibleAssets": "6559000", "earningAssets": "None", "otherCurrentAssets": "51164000", "totalLiabilities": "1169227000", "totalShareholderEquity": "1063636000", "deferredLongTermLiabilities": "None", "otherCurrentLiabilities": "7136000", "commonStock": "183573000", "retainedEarnings": "269568000", "otherLiabilities": "172897000", "goodwill": "21350000", "otherAssets": "98331000", "cash": "273635000", "totalCurrentLiabilities": "277846000", "shortTermDebt": "141112000", "currentLongTermDebt": "141112000", "otherShareholderEquity": "-281267000", "propertyPlantEquipment": "1490298000", "totalCurrentAssets": "660834000", "longTermInvestments": "None", "netTangibleAssets": "1035727000", "shortTermInvestments": "None", "netReceivables": "104420000", "longTermDebt": "718089000", "inventory": "222219000", "accountsPayable": "94643000", "totalPermanentEquity": "None", "additionalPaidInCapital": "None", "commonStockTotalEquity": "None", "preferredStockTotalEquity": "None", "retainedEarningsTotalEquity": "None", "treasuryStock": "-8741000", "accumulatedAmortization": "None", "otherNonCurrrentAssets": "None", "deferredLongTermAssetCharges": "None", "totalNonCurrentAssets": "None", "capitalLeaseObligations": "None", "totalLongTermDebt": "718484000", "otherNonCurrentLiabilities": "None", "totalNonCurrentLiabilities": "None", "negativeGoodwill": "None", "warrants": "None", "preferredStockRedeemable": "None", "capitalSurplus": "900503000", "liabilitiesAndShareholderEquity": "None", "cashAndShortTermInvestments": "273635000", "accumulatedDepreciation": "None", "commonStockSharesOutstanding": "118000000"}, {"fiscalDateEnding": "2018-09-30", "reportedCurrency": "USD", "totalAssets": "2154593000", "intangibleAssets": "5795000", "earningAssets": "None", "otherCurrentAssets": "70272000", "totalLiabilities": "1092156000", "totalShareholderEquity": "1018606000", "deferredLongTermLiabilities": "None", "otherCurrentLiabilities": "13483000", "commonStock": "183573000", "retainedEarnings": "244998000", "otherLiabilities": "164462000", "goodwill": "18396000", "otherAssets": "87911000", "cash": "180828000", "totalCurrentLiabilities": "277933000", "shortTermDebt": "156828000", "currentLongTermDebt": "156828000", "otherShareholderEquity": "-301727000", "propertyPlantEquipment": "1423907000", "totalCurrentAssets": "618584000", "longTermInvestments": "None", "netTangibleAssets": "994415000", "shortTermInvestments": "None", "netReceivables": "128327000", "longTermDebt": "649278000", "inventory": "233461000", "accountsPayable": "69135000", "totalPermanentEquity": "None", "additionalPaidInCapital": "None", "commonStockTotalEquity": "None", "preferredStockTotalEquity": "None", "retainedEarningsTotalEquity": "None", "treasuryStock": "-8741000", "accumulatedAmortization": "None", "otherNonCurrrentAssets": "None", "deferredLongTermAssetCharges": "None", "totalNonCurrentAssets": "None", "capitalLeaseObligations": "None", "totalLongTermDebt": "None", "otherNonCurrentLiabilities": "None", "totalNonCurrentLiabilities": "None", "negativeGoodwill": "None", "warrants": "None", "preferredStockRedeemable": "None", "capitalSurplus": "None", "liabilitiesAndShareholderEquity": "None", "cashAndShortTermInvestments": "None", "accumulatedDepreciation": "None", "commonStockSharesOutstanding": "118000000"}, {"fiscalDateEnding": "2018-06-30", "reportedCurrency": "USD", "totalAssets": "1434167000", "intangibleAssets": "5276000", "earningAssets": "None", "otherCurrentAssets": "63466000", "totalLiabilities": "921328000", "totalShareholderEquity": "508066000", "deferredLongTermLiabilities": "None", "otherCurrentLiabilities": "13890000", "commonStock": "183573000", "retainedEarnings": "36666000", "otherLiabilities": "9306000", "goodwill": "9593000", "otherAssets": "88261000", "cash": "144708000", "totalCurrentLiabilities": "244354000", "shortTermDebt": "142188000", "currentLongTermDebt": "142188000", "otherShareholderEquity": "-603927000", "propertyPlantEquipment": "717517000", "totalCurrentAssets": "613520000", "longTermInvestments": "None", "netTangibleAssets": "493197000", "shortTermInvestments": "71000", "netReceivables": "143057000", "longTermDebt": "667181000", "inventory": "256687000", "accountsPayable": "57376000", "totalPermanentEquity": "None", "additionalPaidInCapital": "None", "commonStockTotalEquity": "None", "preferredStockTotalEquity": "None", "retainedEarningsTotalEquity": "None", "treasuryStock": "-8742000", "accumulatedAmortization": "None", "otherNonCurrrentAssets": "None", "deferredLongTermAssetCharges": "None", "totalNonCurrentAssets": "None", "capitalLeaseObligations": "None", "totalLongTermDebt": "None", "otherNonCurrentLiabilities": "None", "totalNonCurrentLiabilities": "None", "negativeGoodwill": "None", "warrants": "None", "preferredStockRedeemable": "None", "capitalSurplus": "None", "liabilitiesAndShareholderEquity": "None", "cashAndShortTermInvestments": "None", "accumulatedDepreciation": "None", "commonStockSharesOutstanding": "117000000"}, {"fiscalDateEnding": "2018-03-31", "reportedCurrency": "USD", "totalAssets": "1595643000", "intangibleAssets": "4848000", "earningAssets": "None", "otherCurrentAssets": "55684000", "totalLiabilities": "962508000", "totalShareholderEquity": "626559000", "deferredLongTermLiabilities": "None", "otherCurrentLiabilities": "10384000", "commonStock": "183573000", "retainedEarnings": "67897000", "otherLiabilities": "14599000", "goodwill": "12002000", "otherAssets": "65903000", "cash": "183775000", "totalCurrentLiabilities": "304064000", "shortTermDebt": "177699000", "currentLongTermDebt": "177699000", "otherShareholderEquity": "-513386000", "propertyPlantEquipment": "861567000", "totalCurrentAssets": "651323000", "longTermInvestments": "None", "netTangibleAssets": "609709000", "shortTermInvestments": "94000", "netReceivables": "119410000", "longTermDebt": "643808000", "inventory": "275429000", "accountsPayable": "74370000", "totalPermanentEquity": "None", "additionalPaidInCapital": "None", "commonStockTotalEquity": "None", "preferredStockTotalEquity": "None", "retainedEarningsTotalEquity": "None", "treasuryStock": "-9061000", "accumulatedAmortization": "None", "otherNonCurrrentAssets": "None", "deferredLongTermAssetCharges": "None", "totalNonCurrentAssets": "None", "capitalLeaseObligations": "None", "totalLongTermDebt": "None", "otherNonCurrentLiabilities": "None", "totalNonCurrentLiabilities": "None", "negativeGoodwill": "None", "warrants": "None", "preferredStockRedeemable": "None", "capitalSurplus": "None", "liabilitiesAndShareholderEquity": "None", "cashAndShortTermInvestments": "None", "accumulatedDepreciation": "None", "commonStockSharesOutstanding": "117000000"}, {"fiscalDateEnding": "2017-12-31", "reportedCurrency": "USD", "totalAssets": "1607201000", "intangibleAssets": "17192000", "earningAssets": "None", "otherCurrentAssets": "52575000", "totalLiabilities": "962070000", "totalShareholderEquity": "639714000", "deferredLongTermLiabilities": "10457000", "otherCurrentLiabilities": "44183000", "commonStock": "183573000", "retainedEarnings": "60984000", "otherLiabilities": "6145000", "goodwill": "12412000", "otherAssets": "96818000", "cash": "269195000", "totalCurrentLiabilities": "282408000", "shortTermDebt": "148617000", "currentLongTermDebt": "148617000", "otherShareholderEquity": "-506810000", "propertyPlantEquipment": "820931000", "totalCurrentAssets": "689452000", "longTermInvestments": "24378000", "netTangibleAssets": "622522000", "shortTermInvestments": "380000", "netReceivables": "101665000", "longTermDebt": "663060000", "inventory": "265637000", "accountsPayable": "82824000", "totalPermanentEquity": "None", "additionalPaidInCapital": "None", "commonStockTotalEquity": "None", "preferredStockTotalEquity": "None", "retainedEarningsTotalEquity": "None", "treasuryStock": "-6967000", "accumulatedAmortization": "None", "otherNonCurrrentAssets": "None", "deferredLongTermAssetCharges": "None", "totalNonCurrentAssets": "None", "capitalLeaseObligations": "None", "totalLongTermDebt": "None", "otherNonCurrentLiabilities": "None", "totalNonCurrentLiabilities": "None", "negativeGoodwill": "None", "warrants": "None", "preferredStockRedeemable": "None", "capitalSurplus": "None", "liabilitiesAndShareholderEquity": "None", "cashAndShortTermInvestments": "None", "accumulatedDepreciation": "None", "commonStockSharesOutstanding": "121000000"}, {"fiscalDateEnding": "2017-09-30", "reportedCurrency": "USD", "totalAssets": "1941548000", "intangibleAssets": "17658000", "earningAssets": "None", "otherCurrentAssets": "58311000", "totalLiabilities": "1251696000", "totalShareholderEquity": "683392000", "deferredLongTermLiabilities": "None", "otherCurrentLiabilities": "46813000", "commonStock": "183573000", "retainedEarnings": "56682000", "otherLiabilities": "6130000", "goodwill": "13124000", "otherAssets": "90664000", "cash": "523175000", "totalCurrentLiabilities": "305484000", "shortTermDebt": "179523000", "currentLongTermDebt": "179523000", "otherShareholderEquity": "-485855000", "propertyPlantEquipment": "847443000", "totalCurrentAssets": "1003441000", "longTermInvestments": "None", "netTangibleAssets": "665734000", "shortTermInvestments": "7000", "netReceivables": "151013000", "longTermDebt": "925589000", "inventory": "270935000", "accountsPayable": "63830000", "totalPermanentEquity": "None", "additionalPaidInCapital": "None", "commonStockTotalEquity": "None", "preferredStockTotalEquity": "None", "retainedEarningsTotalEquity": "None", "treasuryStock": "-2759000", "accumulatedAmortization": "None", "otherNonCurrrentAssets": "None", "deferredLongTermAssetCharges": "None", "totalNonCurrentAssets": "None", "capitalLeaseObligations": "None", "totalLongTermDebt": "None", "otherNonCurrentLiabilities": "None", "totalNonCurrentLiabilities": "None", "negativeGoodwill": "None", "warrants": "None", "preferredStockRedeemable": "None", "capitalSurplus": "None", "liabilitiesAndShareholderEquity": "None", "cashAndShortTermInvestments": "None", "accumulatedDepreciation": "None", "commonStockSharesOutstanding": "68000000"}, {"fiscalDateEnding": "2017-06-30", "reportedCurrency": "USD", "totalAssets": "1571541000", "intangibleAssets": "16966000", "earningAssets": "None", "otherCurrentAssets": "53489000", "totalLiabilities": "908620000", "totalShareholderEquity": "656251000", "deferredLongTermLiabilities": "None", "otherCurrentLiabilities": "39790000", "commonStock": "183573000", "retainedEarnings": "59692000", "otherLiabilities": "6576000", "goodwill": "13031000", "otherAssets": "84117000", "cash": "219934000", "totalCurrentLiabilities": "350069000", "shortTermDebt": "794279000", "currentLongTermDebt": "794279000", "otherShareholderEquity": "-518607000", "propertyPlantEquipment": "837360000", "totalCurrentAssets": "650064000", "longTermInvestments": "None", "netTangibleAssets": "639285000", "shortTermInvestments": "1179000", "netReceivables": "130765000", "longTermDebt": "537484000", "inventory": "244697000", "accountsPayable": "51023000", "totalPermanentEquity": "None", "additionalPaidInCapital": "None", "commonStockTotalEquity": "None", "preferredStockTotalEquity": "None", "retainedEarningsTotalEquity": "None", "treasuryStock": "-2368000", "accumulatedAmortization": "None", "otherNonCurrrentAssets": "None", "deferredLongTermAssetCharges": "None", "totalNonCurrentAssets": "None", "capitalLeaseObligations": "None", "totalLongTermDebt": "None", "otherNonCurrentLiabilities": "None", "totalNonCurrentLiabilities": "None", "negativeGoodwill": "None", "warrants": "None", "preferredStockRedeemable": "None", "capitalSurplus": "None", "liabilitiesAndShareholderEquity": "None", "cashAndShortTermInvestments": "None", "accumulatedDepreciation": "None", "commonStockSharesOutstanding": "123000000"}, {"fiscalDateEnding": "2017-03-31", "reportedCurrency": "USD", "totalAssets": "1636507000", "intangibleAssets": "17640000", "earningAssets": "None", "otherCurrentAssets": "54423000", "totalLiabilities": "934223000", "totalShareholderEquity": "695175000", "deferredLongTermLiabilities": "None", "otherCurrentLiabilities": "44905000", "commonStock": "183573000", "retainedEarnings": "55989000", "otherLiabilities": "7439000", "goodwill": "13807000", "otherAssets": "82429000", "cash": "231321000", "totalCurrentLiabilities": "343970000", "shortTermDebt": "795820000", "currentLongTermDebt": "795820000", "otherShareholderEquity": "-478548000", "propertyPlantEquipment": "872816000", "totalCurrentAssets": "681262000", "longTermInvestments": "None", "netTangibleAssets": "677535000", "shortTermInvestments": "3506000", "netReceivables": "134638000", "longTermDebt": "565607000", "inventory": "257374000", "accountsPayable": "66688000", "totalPermanentEquity": "None", "additionalPaidInCapital": "None", "commonStockTotalEquity": "None", "preferredStockTotalEquity": "None", "retainedEarningsTotalEquity": "None", "treasuryStock": "-2030000", "accumulatedAmortization": "None", "otherNonCurrrentAssets": "None", "deferredLongTermAssetCharges": "None", "totalNonCurrentAssets": "None", "capitalLeaseObligations": "None", "totalLongTermDebt": "None", "otherNonCurrentLiabilities": "None", "totalNonCurrentLiabilities": "None", "negativeGoodwill": "None", "warrants": "None", "preferredStockRedeemable": "None", "capitalSurplus": "None", "liabilitiesAndShareholderEquity": "None", "cashAndShortTermInvestments": "None", "accumulatedDepreciation": "None", "commonStockSharesOutstanding": "122000000"}, {"fiscalDateEnding": "2016-12-31", "reportedCurrency": "USD", "totalAssets": "1455766000", "intangibleAssets": "17252000", "earningAssets": "None", "otherCurrentAssets": "33175000", "totalLiabilities": "784093000", "totalShareholderEquity": "664091000", "deferredLongTermLiabilities": "14689000", "otherCurrentLiabilities": "48673000", "commonStock": "183573000", "retainedEarnings": "50998000", "otherLiabilities": "6623000", "goodwill": "13405000", "otherAssets": "84998000", "cash": "158568000", "totalCurrentLiabilities": "332477000", "shortTermDebt": "204923000", "currentLongTermDebt": "204923000", "otherShareholderEquity": "-505871000", "propertyPlantEquipment": "802608000", "totalCurrentAssets": "568160000", "longTermInvestments": "20078000", "netTangibleAssets": "646839000", "shortTermInvestments": "3546000", "netReceivables": "124229000", "longTermDebt": "430304000", "inventory": "248642000", "accountsPayable": "77325000", "totalPermanentEquity": "None", "additionalPaidInCapital": "None", "commonStockTotalEquity": "None", "preferredStockTotalEquity": "None", "retainedEarningsTotalEquity": "None", "treasuryStock": "-1859000", "accumulatedAmortization": "None", "otherNonCurrrentAssets": "None", "deferredLongTermAssetCharges": "None", "totalNonCurrentAssets": "None", "capitalLeaseObligations": "None", "totalLongTermDebt": "None", "otherNonCurrentLiabilities": "None", "totalNonCurrentLiabilities": "None", "negativeGoodwill": "None", "warrants": "None", "preferredStockRedeemable": "None", "capitalSurplus": "None", "liabilitiesAndShareholderEquity": "None", "cashAndShortTermInvestments": "None", "accumulatedDepreciation": "None", "commonStockSharesOutstanding": "123000000"}, {"fiscalDateEnding": "2016-09-30", "reportedCurrency": "USD", "totalAssets": "1565661000", "intangibleAssets": "17572000", "earningAssets": "None", "otherCurrentAssets": "47264000", "totalLiabilities": "917543000", "totalShareholderEquity": "640349000", "deferredLongTermLiabilities": "None", "otherCurrentLiabilities": "54997000", "commonStock": "183573000", "retainedEarnings": "39101000", "otherLiabilities": "7932000", "goodwill": "13661000", "otherAssets": "85082000", "cash": "136482000", "totalCurrentLiabilities": "455651000", "shortTermDebt": "776789000", "currentLongTermDebt": "776789000", "otherShareholderEquity": "None", "propertyPlantEquipment": "815592000", "totalCurrentAssets": "664987000", "longTermInvestments": "None", "netTangibleAssets": "None", "shortTermInvestments": "2187000", "netReceivables": "184669000", "longTermDebt": "439188000", "inventory": "294385000", "accountsPayable": "59193000", "totalPermanentEquity": "None", "additionalPaidInCapital": "None", "commonStockTotalEquity": "None", "preferredStockTotalEquity": "None", "retainedEarningsTotalEquity": "None", "treasuryStock": "-1342000", "accumulatedAmortization": "None", "otherNonCurrrentAssets": "None", "deferredLongTermAssetCharges": "None", "totalNonCurrentAssets": "None", "capitalLeaseObligations": "None", "totalLongTermDebt": "None", "otherNonCurrentLiabilities": "None", "totalNonCurrentLiabilities": "None", "negativeGoodwill": "None", "warrants": "None", "preferredStockRedeemable": "None", "capitalSurplus": "None", "liabilitiesAndShareholderEquity": "None", "cashAndShortTermInvestments": "None", "accumulatedDepreciation": "None", "commonStockSharesOutstanding": "124000000"}, {"fiscalDateEnding": "2016-06-30", "reportedCurrency": "USD", "totalAssets": "1566649000", "intangibleAssets": "17778000", "earningAssets": "None", "otherCurrentAssets": "44194000", "totalLiabilities": "937610000", "totalShareholderEquity": "621346000", "deferredLongTermLiabilities": "None", "otherCurrentLiabilities": "66829000", "commonStock": "183573000", "retainedEarnings": "33000000", "otherLiabilities": "4307000", "goodwill": "13855000", "otherAssets": "94135000", "cash": "167587000", "totalCurrentLiabilities": "424962000", "shortTermDebt": "791000000", "currentLongTermDebt": "791000000", "otherShareholderEquity": "None", "propertyPlantEquipment": "830705000", "totalCurrentAssets": "642000000", "longTermInvestments": "None", "netTangibleAssets": "None", "shortTermInvestments": "14519000", "netReceivables": "144000000", "longTermDebt": "494201000", "inventory": "271264000", "accountsPayable": "58632000", "totalPermanentEquity": "None", "additionalPaidInCapital": "None", "commonStockTotalEquity": "None", "preferredStockTotalEquity": "None", "retainedEarningsTotalEquity": "None", "treasuryStock": "-1201000", "accumulatedAmortization": "None", "otherNonCurrrentAssets": "None", "deferredLongTermAssetCharges": "None", "totalNonCurrentAssets": "None", "capitalLeaseObligations": "None", "totalLongTermDebt": "None", "otherNonCurrentLiabilities": "None", "totalNonCurrentLiabilities": "None", "negativeGoodwill": "None", "warrants": "None", "preferredStockRedeemable": "None", "capitalSurplus": "None", "liabilitiesAndShareholderEquity": "None", "cashAndShortTermInvestments": "None", "accumulatedDepreciation": "None", "commonStockSharesOutstanding": "122000000"}, {"fiscalDateEnding": "2016-03-31", "reportedCurrency": "USD", "totalAssets": "1500602000", "intangibleAssets": "17082000", "earningAssets": "None", "otherCurrentAssets": "34957000", "totalLiabilities": "928674000", "totalShareholderEquity": "564288000", "deferredLongTermLiabilities": "None", "otherCurrentLiabilities": "40879000", "commonStock": "183573000", "retainedEarnings": "50000000", "otherLiabilities": "4900000", "goodwill": "13277000", "otherAssets": "122304000", "cash": "223688000", "totalCurrentLiabilities": "392233000", "shortTermDebt": "795000000", "currentLongTermDebt": "795000000", "otherShareholderEquity": "None", "propertyPlantEquipment": "761283000", "totalCurrentAssets": "617000000", "longTermInvestments": "None", "netTangibleAssets": "None", "shortTermInvestments": "8020000", "netReceivables": "144000000", "longTermDebt": "511705000", "inventory": "206496000", "accountsPayable": "55890000", "totalPermanentEquity": "None", "additionalPaidInCapital": "None", "commonStockTotalEquity": "None", "preferredStockTotalEquity": "None", "retainedEarningsTotalEquity": "None", "treasuryStock": "-1907000", "accumulatedAmortization": "None", "otherNonCurrrentAssets": "None", "deferredLongTermAssetCharges": "None", "totalNonCurrentAssets": "None", "capitalLeaseObligations": "None", "totalLongTermDebt": "None", "otherNonCurrentLiabilities": "None", "totalNonCurrentLiabilities": "None", "negativeGoodwill": "None", "warrants": "None", "preferredStockRedeemable": "None", "capitalSurplus": "None", "liabilitiesAndShareholderEquity": "None", "cashAndShortTermInvestments": "None", "accumulatedDepreciation": "None", "commonStockSharesOutstanding": "160000000"}, {"fiscalDateEnding": "2015-12-31", "reportedCurrency": "USD", "totalAssets": "1370705000", "intangibleAssets": "16661000", "earningAssets": "None", "otherCurrentAssets": "20945000", "totalLiabilities": "827975000", "totalShareholderEquity": "535395000", "deferredLongTermLiabilities": "15636000", "otherCurrentLiabilities": "36084000", "commonStock": "183573000", "retainedEarnings": "48795000", "otherLiabilities": "4919000", "goodwill": "13510000", "otherAssets": "357765000", "cash": "198894000", "totalCurrentLiabilities": "323769000", "shortTermDebt": "239468000", "currentLongTermDebt": "239468000", "otherShareholderEquity": "-648022000", "propertyPlantEquipment": "540218000", "totalCurrentAssets": "539382000", "longTermInvestments": "26591000", "netTangibleAssets": "503423000", "shortTermInvestments": "6000", "netReceivables": "128909000", "longTermDebt": "483651000", "inventory": "123968000", "accountsPayable": "47035000", "totalPermanentEquity": "None", "additionalPaidInCapital": "None", "commonStockTotalEquity": "None", "preferredStockTotalEquity": "None", "retainedEarningsTotalEquity": "None", "treasuryStock": "-1936000", "accumulatedAmortization": "None", "otherNonCurrrentAssets": "None", "deferredLongTermAssetCharges": "None", "totalNonCurrentAssets": "None", "capitalLeaseObligations": "None", "totalLongTermDebt": "None", "otherNonCurrentLiabilities": "None", "totalNonCurrentLiabilities": "None", "negativeGoodwill": "None", "warrants": "None", "preferredStockRedeemable": "None", "capitalSurplus": "None", "liabilitiesAndShareholderEquity": "None", "cashAndShortTermInvestments": "None", "accumulatedDepreciation": "None", "commonStockSharesOutstanding": "112000000"}, {"fiscalDateEnding": "2015-09-30", "reportedCurrency": "USD", "totalAssets": "1483555000", "intangibleAssets": "19499000", "earningAssets": "None", "otherCurrentAssets": "35137000", "totalLiabilities": "942247000", "totalShareholderEquity": "533693000", "deferredLongTermLiabilities": "None", "otherCurrentLiabilities": "52434000", "commonStock": "183573000", "retainedEarnings": "None", "otherLiabilities": "5251000", "goodwill": "16204000", "otherAssets": "359521000", "cash": "224349000", "totalCurrentLiabilities": "346799000", "shortTermDebt": "None", "currentLongTermDebt": "None", "otherShareholderEquity": "None", "propertyPlantEquipment": "578210000", "totalCurrentAssets": "None", "longTermInvestments": "None", "netTangibleAssets": "None", "shortTermInvestments": "23000", "netReceivables": "None", "longTermDebt": "562585000", "inventory": "165172000", "accountsPayable": "46932000", "totalPermanentEquity": "None", "additionalPaidInCapital": "None", "commonStockTotalEquity": "None", "preferredStockTotalEquity": "None", "retainedEarningsTotalEquity": "None", "treasuryStock": "-1977000", "accumulatedAmortization": "None", "otherNonCurrrentAssets": "None", "deferredLongTermAssetCharges": "None", "totalNonCurrentAssets": "None", "capitalLeaseObligations": "None", "totalLongTermDebt": "None", "otherNonCurrentLiabilities": "None", "totalNonCurrentLiabilities": "None", "negativeGoodwill": "None", "warrants": "None", "preferredStockRedeemable": "None", "capitalSurplus": "None", "liabilitiesAndShareholderEquity": "None", "cashAndShortTermInvestments": "None", "accumulatedDepreciation": "None", "commonStockSharesOutstanding": "123000000"}, {"fiscalDateEnding": "2015-06-30", "reportedCurrency": "USD", "totalAssets": "1613880000", "intangibleAssets": "22033000", "earningAssets": "None", "otherCurrentAssets": "36092000", "totalLiabilities": "926709000", "totalShareholderEquity": "679306000", "deferredLongTermLiabilities": "None", "otherCurrentLiabilities": "55992000", "commonStock": "183573000", "retainedEarnings": "None", "otherLiabilities": "5440000", "goodwill": "18246000", "otherAssets": "406788000", "cash": "163466000", "totalCurrentLiabilities": "331605000", "shortTermDebt": "None", "currentLongTermDebt": "None", "otherShareholderEquity": "None", "propertyPlantEquipment": "713824000", "totalCurrentAssets": "None", "longTermInvestments": "None", "netTangibleAssets": "None", "shortTermInvestments": "28000", "netReceivables": "None", "longTermDebt": "554677000", "inventory": "168734000", "accountsPayable": "43889000", "totalPermanentEquity": "None", "additionalPaidInCapital": "None", "commonStockTotalEquity": "None", "preferredStockTotalEquity": "None", "retainedEarningsTotalEquity": "None", "treasuryStock": "-1943000", "accumulatedAmortization": "None", "otherNonCurrrentAssets": "None", "deferredLongTermAssetCharges": "None", "totalNonCurrentAssets": "None", "capitalLeaseObligations": "None", "totalLongTermDebt": "None", "otherNonCurrentLiabilities": "None", "totalNonCurrentLiabilities": "None", "negativeGoodwill": "None", "warrants": "None", "preferredStockRedeemable": "None", "capitalSurplus": "None", "liabilitiesAndShareholderEquity": "None", "cashAndShortTermInvestments": "None", "accumulatedDepreciation": "None", "commonStockSharesOutstanding": "120000000"}]}